speechcraft/__init__.py
speechcraft/cli.py
speechcraft/server.py
speechcraft/settings.py
speechcraft/text2voice.py
speechcraft/voice2voice.py
speechcraft/assets/prompts/announcer.npz
speechcraft/assets/prompts/de_speaker_0.npz
speechcraft/assets/prompts/de_speaker_1.npz
speechcraft/assets/prompts/de_speaker_2.npz
speechcraft/assets/prompts/de_speaker_3.npz
speechcraft/assets/prompts/de_speaker_4.npz
speechcraft/assets/prompts/de_speaker_5.npz
speechcraft/assets/prompts/de_speaker_6.npz
speechcraft/assets/prompts/de_speaker_7.npz
speechcraft/assets/prompts/de_speaker_8.npz
speechcraft/assets/prompts/de_speaker_9.npz
speechcraft/assets/prompts/en_speaker_0.npz
speechcraft/assets/prompts/en_speaker_1.npz
speechcraft/assets/prompts/en_speaker_2.npz
speechcraft/assets/prompts/en_speaker_3.npz
speechcraft/assets/prompts/en_speaker_4.npz
speechcraft/assets/prompts/en_speaker_5.npz
speechcraft/assets/prompts/en_speaker_6.npz
speechcraft/assets/prompts/en_speaker_7.npz
speechcraft/assets/prompts/en_speaker_8.npz
speechcraft/assets/prompts/en_speaker_9.npz
speechcraft/assets/prompts/es_speaker_0.npz
speechcraft/assets/prompts/es_speaker_1.npz
speechcraft/assets/prompts/es_speaker_2.npz
speechcraft/assets/prompts/es_speaker_3.npz
speechcraft/assets/prompts/es_speaker_4.npz
speechcraft/assets/prompts/es_speaker_5.npz
speechcraft/assets/prompts/es_speaker_6.npz
speechcraft/assets/prompts/es_speaker_7.npz
speechcraft/assets/prompts/es_speaker_8.npz
speechcraft/assets/prompts/es_speaker_9.npz
speechcraft/assets/prompts/fr_speaker_0.npz
speechcraft/assets/prompts/fr_speaker_1.npz
speechcraft/assets/prompts/fr_speaker_2.npz
speechcraft/assets/prompts/fr_speaker_3.npz
speechcraft/assets/prompts/fr_speaker_4.npz
speechcraft/assets/prompts/fr_speaker_5.npz
speechcraft/assets/prompts/fr_speaker_6.npz
speechcraft/assets/prompts/fr_speaker_7.npz
speechcraft/assets/prompts/fr_speaker_8.npz
speechcraft/assets/prompts/fr_speaker_9.npz
speechcraft/assets/prompts/hermine.npz
speechcraft-0.0.19.dist-info/licenses/LICENSE
speechcraft-0.0.19.dist-info/METADATA
speechcraft-0.0.19.dist-info/WHEEL
speechcraft-0.0.19.dist-info/top_level.txt
speechcraft-0.0.19.dist-info/RECORD
