Metadata-Version: 2.4
Name: SpeechCraft
Version: 0.0.19
Summary: Create natural sounding audio from text, clone voices and use them. Convert voice to voice. Bark model.
Author: SocAIty
License: MIT License
Project-URL: source, https://github.com/SocAIty/SpeechCraft
Requires-Python: >=3.8
License-File: LICENSE
Requires-Dist: media-toolkit[AudioFile]>=00.02.08
Requires-Dist: encodec
Requires-Dist: fairseq==0.12.2
Requires-Dist: boto3
Requires-Dist: funcy
Requires-Dist: huggingface-hub>=0.14.1
Requires-Dist: numpy
Requires-Dist: scipy
Requires-Dist: tokenizers
Requires-Dist: torch
Requires-Dist: torchaudio
Requires-Dist: tqdm
Requires-Dist: transformers
Requires-Dist: omegaconf<2.1,>=2.0.5
Provides-Extra: full
Requires-Dist: fastapi; extra == "full"
Requires-Dist: fast-task-api>=1.1.9; extra == "full"
Provides-Extra: dev
Requires-Dist: fastapi; extra == "dev"
Requires-Dist: fast-task-api>=1.1.9; extra == "dev"
Requires-Dist: pytest>=7.0.0; extra == "dev"
Requires-Dist: pytest-cov>=4.0.0; extra == "dev"
Dynamic: license-file
